mngfiles/__init__.py
mngfiles/mngfiles.py
mngfiles-1.0.1.dist-info/METADATA
mngfiles-1.0.1.dist-info/WHEEL
mngfiles-1.0.1.dist-info/top_level.txt
mngfiles-1.0.1.dist-info/RECORD
