Metadata-Version: 2.1
Name: mngfiles
Version: 1.0.1
Summary: Manage Files for s3
Home-page: https://github.com/facundommay
Author: Facundo Maldonado
Author-email: facundommay@gmail.com
License: MIT
Requires-Dist: boto3
Requires-Dist: botocore
